aio_swagger/__init__.py
aio_swagger/helpers/__init__.py
aio_swagger/helpers/builders.py
aio_swagger/helpers/decorators.py
aio_swagger/swagger_ui/index.html
aio_swagger/swagger_ui/o2c.html
aio_swagger/swagger_ui/swagger-ui.js
aio_swagger/swagger_ui/css/print.css
aio_swagger/swagger_ui/css/reset.css
aio_swagger/swagger_ui/css/screen.css
aio_swagger/swagger_ui/css/style.css
aio_swagger/swagger_ui/css/typography.css
aio_swagger/swagger_ui/fonts/DroidSans-Bold.ttf
aio_swagger/swagger_ui/fonts/DroidSans.ttf
aio_swagger/swagger_ui/images/collapse.gif
aio_swagger/swagger_ui/images/expand.gif
aio_swagger/swagger_ui/images/explorer_icons.png
aio_swagger/swagger_ui/images/favicon-16x16.png
aio_swagger/swagger_ui/images/favicon-32x32.png
aio_swagger/swagger_ui/images/favicon.ico
aio_swagger/swagger_ui/images/logo_small.png
aio_swagger/swagger_ui/images/pet_store_api.png
aio_swagger/swagger_ui/images/throbber.gif
aio_swagger/swagger_ui/images/wordnik_api.png
aio_swagger/swagger_ui/lang/ca.js
aio_swagger/swagger_ui/lang/en.js
aio_swagger/swagger_ui/lang/es.js
aio_swagger/swagger_ui/lang/fr.js
aio_swagger/swagger_ui/lang/geo.js
aio_swagger/swagger_ui/lang/it.js
aio_swagger/swagger_ui/lang/ja.js
aio_swagger/swagger_ui/lang/ko-kr.js
aio_swagger/swagger_ui/lang/pl.js
aio_swagger/swagger_ui/lang/pt.js
aio_swagger/swagger_ui/lang/ru.js
aio_swagger/swagger_ui/lang/tr.js
aio_swagger/swagger_ui/lang/translator.js
aio_swagger/swagger_ui/lang/zh-cn.js
aio_swagger/swagger_ui/lib/backbone-min.js
aio_swagger/swagger_ui/lib/es5-shim.js
aio_swagger/swagger_ui/lib/handlebars-4.0.5.js
aio_swagger/swagger_ui/lib/highlight.9.1.0.pack.js
aio_swagger/swagger_ui/lib/highlight.9.1.0.pack_extended.js
aio_swagger/swagger_ui/lib/jquery-1.8.0.min.js
aio_swagger/swagger_ui/lib/jquery.ba-bbq.min.js
aio_swagger/swagger_ui/lib/jquery.slideto.min.js
aio_swagger/swagger_ui/lib/jquery.wiggle.min.js
aio_swagger/swagger_ui/lib/js-yaml.min.js
aio_swagger/swagger_ui/lib/jsoneditor.min.js
aio_swagger-0.5.dist-info/METADATA
aio_swagger-0.5.dist-info/WHEEL
aio_swagger-0.5.dist-info/top_level.txt
aio_swagger-0.5.dist-info/RECORD
