Metadata-Version: 2.1
Name: aio-swagger
Version: 0.5
Summary: UNKNOWN
Home-page: https://gitlab.homecred.it/internal/aio-swagger
Author: Alexey Shkil
Author-email: aleksey.shkil@homecredit.ru
License: UNKNOWN
Platform: UNKNOWN
Requires-Dist: pyyaml
Requires-Dist: jinja2
Requires-Dist: aiohttp
